{"Version": "4KEasy", "AudioFilename": "RWBY-Thiswillbetheday.mp3", "StackLeniency": "0.7", "Countdown": "0", "BeatDivisor": "2", "SliderTickRate": "3", "CircleSize": "4", "WidescreenStoryboard": "1", "Mode": "3", "OverallDifficulty": "7", "AudioLeadIn": "0", "HPDrainRate": "7", "BeatmapSetID": "130556", "Artist": "JeffWilliams", "DistanceSpacing": "1.2", "GridSize": "4", "PreviewTime": "38000", "BeatmapID": "360806", "TitleUnicode": "ThisWillBetheDay(feat.CaseyLeeWilliams)", "SampleSet": "Normal", "SpecialStyle": "0", "Title": "ThisWillBetheDay(feat.CaseyLeeWilliams)", "LetterboxInBreaks": "0", "Creator": "arcwinolivirus", "Source": "RWBY", "ArtistUnicode": "JeffWilliams", "Tags": "openingroosterteeth-DanteMayCry-", "SliderMultiplier": "1.6", "ApproachRate": "9"}
